exopropred/Data/AAIndexNames.csv
exopropred/Data/Grantham.csv
exopropred/Data/PhysicoChemical.csv
exopropred/Data/PhysicoChemical_X.csv
exopropred/Data/Schneider-Wrede.csv
exopropred/Data/aa_attr_group.csv
exopropred/Data/aaind.txt
exopropred/Data/aaindex.csv
exopropred/Data/aaindex_X.csv
exopropred/Data/aaindices.csv
exopropred/Data/atom.csv
exopropred/Data/bin_di.csv
exopropred/Data/bonds.csv
exopropred/Data/can_pat.csv
exopropred/Data/data
exopropred/Data/z_aaindex.csv
exopropred/blast_binaries/linux/psiblast
exopropred/blast_binaries/mac/psiblast
exopropred/blast_binaries/windows/nghttp2.dll
exopropred/blast_binaries/windows/psiblast.exe
exopropred/extra/featureGenerator.py
exopropred/extra/featureGenerator.pyc
exopropred/extra/headerHandler.py
exopropred/extra/matrixTransformer.py
exopropred/extra/matrixTransformer.pyc
exopropred/extra/possum.py
exopropred/extra/possum_ft.py
exopropred/extra/possum_ft.pyc
exopropred/model/RF_model.zip
exopropred/perl_scripts/MERCI_motif_locator.pl
exopropred/python_scripts/__init__.py
exopropred/python_scripts/exopropred.py
exopropred-1.1.dist-info/LICENSE.txt
exopropred-1.1.dist-info/METADATA
exopropred-1.1.dist-info/WHEEL
exopropred-1.1.dist-info/entry_points.txt
exopropred-1.1.dist-info/top_level.txt
exopropred-1.1.dist-info/RECORD
