Metadata-Version: 2.1
Name: exopropred
Version: 1.1
Summary: A tool to predict the subcellular localisation of exosomal proteins
Home-page: https://github.com/raghavagps/exopropred
Requires-Python: >=3.6
License-File: LICENSE.txt
Requires-Dist: numpy
Requires-Dist: pandas
Requires-Dist: argparse
Requires-Dist: scikit-learn
